bubble3/__init__.py
bubble3/cli.py
bubble3/functions.py
bubble3/functions_system.py
bubble3/metadata.py
bubble3/rules.py
bubble3/transformer.py
bubble3/clients/__init__.py
bubble3/commands/__init__.py
bubble3/commands/cmd_config.py
bubble3/commands/cmd_examples.py
bubble3/commands/cmd_export.py
bubble3/commands/cmd_functions.py
bubble3/commands/cmd_init.py
bubble3/commands/cmd_listen.py
bubble3/commands/cmd_manual.py
bubble3/commands/cmd_pipe.py
bubble3/commands/cmd_promote.py
bubble3/commands/cmd_pull.py
bubble3/commands/cmd_pump.py
bubble3/commands/cmd_push.py
bubble3/commands/cmd_rules.py
bubble3/commands/cmd_stats.py
bubble3/commands/cmd_transform.py
bubble3/commands/cmd_upgrade.py
bubble3/commands/cmd_web.py
bubble3/util/__init__.py
bubble3/util/buts.py
bubble3/util/cfg.py
bubble3/util/cli_misc.py
bubble3/util/counter.py
bubble3/util/delta.py
bubble3/util/escapes.py
bubble3/util/examples.py
bubble3/util/flat_dict.py
bubble3/util/generators.py
bubble3/util/inside_try.py
bubble3/util/magic.py
bubble3/util/profiling.py
bubble3/util/value_path.py
bubble3/util/zipit.py
bubble3/util/dataset/__init__.py
bubble3/util/dataset/convert.py
bubble3/util/store/__init__.py
bubble3/util/store/convert.py
bubble3/util/store/storage_type_json.py
bubble3/util/store/storage_type_jsonl.py
bubble3-2018.6.4.dist-info/DESCRIPTION.rst
bubble3-2018.6.4.dist-info/METADATA
bubble3-2018.6.4.dist-info/RECORD
bubble3-2018.6.4.dist-info/WHEEL
bubble3-2018.6.4.dist-info/entry_points.txt
bubble3-2018.6.4.dist-info/metadata.json
bubble3-2018.6.4.dist-info/top_level.txt
