Metadata-Version: 2.0
Name: bubble3
Version: 2018.6.4
Summary: cli tool to bubble information from one to another service, with rule based transformations ">>>"
Home-page: https://github.com/e7dal/bubble3
Author: Erdal Yildiz
Author-email: erdalyildiz1974@gmail.com
License: GPL-3.0
Keywords: bubble,api2api,transform
Platform: UNKNOWN
Classifier: Development Status :: 4 - Beta
Classifier: Intended Audience :: Developers
Classifier: Operating System :: POSIX :: Linux
Classifier: Environment :: Console
Classifier: Programming Language :: Python :: 3.6
Requires-Dist: arrow (==0.12.1)
Requires-Dist: click (==6.7)
Requires-Dist: et-xmlfile (==1.0.1)
Requires-Dist: jdcal (==1.4)
Requires-Dist: odfpy (==1.3.6)
Requires-Dist: openpyxl (==2.5.3)
Requires-Dist: path.py (==11.0.1)
Requires-Dist: python-dateutil (==2.7.3)
Requires-Dist: pyyaml (==3.12)
Requires-Dist: simplejson (==3.15.0)
Requires-Dist: six (==1.11.0)
Requires-Dist: tablib (==0.12.1)
Requires-Dist: unicodecsv (==0.14.1)
Requires-Dist: wheel (==0.31.1)
Requires-Dist: xlrd (==1.1.0)
Requires-Dist: xlwt (==1.3.0)
